README.txt
setup.cfg
setup.py
Products/__init__.py
Products.VisitTracker.egg-info/PKG-INFO
Products.VisitTracker.egg-info/SOURCES.txt
Products.VisitTracker.egg-info/dependency_links.txt
Products.VisitTracker.egg-info/entry_points.txt
Products.VisitTracker.egg-info/namespace_packages.txt
Products.VisitTracker.egg-info/not-zip-safe
Products.VisitTracker.egg-info/requires.txt
Products.VisitTracker.egg-info/top_level.txt
Products/VisitTracker/__init__.py
Products/VisitTracker/adapter.py
Products/VisitTracker/configure.zcml
Products/VisitTracker/interfaces.py
docs/HISTORY.txt