Metadata-Version: 1.0
Name: Products.VisitTracker
Version: 1.0b2
Summary: Utility to track visits
Home-page: http://raptus.com
Author: Raptus AG
Author-email: dev@raptus.com
License: GPL
Platform: UNKNOWN
Classifier: Programming Language :: Python
Classifier: Topic :: Software Development :: Libraries :: Python Modules
